{
    "keep": {
        "days": true,
        "amount": 14
    },
    "auditLog": "C:\\Users\\sinab\\Desktop\\bookmania-server\\logs\\winston\\successes\\.360fe41564f1a4d3af04ce0afab560295e153609-audit.json",
    "files": [
        {
            "date": 1738786373960,
            "name": "C:\\Users\\sinab\\Desktop\\bookmania-server\\logs\\winston\\successes\\phu-2025-06-02-02-success.log",
            "hash": "e2f56179a430f09bdd0998feee4cf03fd411e50f49a8aede0826a723aea2c3c2"
        },
        {
            "date": 1738789453423,
            "name": "C:\\Users\\sinab\\Desktop\\bookmania-server\\logs\\winston\\successes\\phu-2025-06-02-03-success.log",
            "hash": "fbc1531c6101bec7a0a7e440f958261572d917c0dfff165290ebfc929958c9fb"
        }
    ],
    "hashType": "sha256"
}